omniregress/__init__.py
omniregress/linear_regression.py
omniregress/polynomial_regression.py
omnirgress-1.1.0.dist-info/licenses/LICENSE
omnirgress-1.1.0.dist-info/METADATA
omnirgress-1.1.0.dist-info/WHEEL
omnirgress-1.1.0.dist-info/top_level.txt
omnirgress-1.1.0.dist-info/RECORD
