Metadata-Version: 2.4
Name: omnirgress
Version: 1.1.0
Summary: OmniRegress: A comprehensive Python library for all types of regression analysis.
Author-email: "Maaz.waheed" <maaz.waheed@mbktechstudio.com>
License: MPL-2.0
Project-URL: Homepage, https://github.com/42Wor/omniregress
Project-URL: Repository, https://github.com/42Wor/omniregress
Keywords: regression,machine learning,statistics,data analysis,python,omni,omnirgress
Classifier: Development Status :: 3 - Alpha
Classifier: Intended Audience :: Developers
Classifier: Intended Audience :: Science/Research
Classifier: Topic :: Scientific/Engineering :: Artificial Intelligence
Classifier: Topic :: Scientific/Engineering :: Information Analysis
Classifier: Topic :: Scientific/Engineering :: Mathematics
Classifier: Topic :: Software Development :: Libraries :: Python Modules
Classifier: License :: OSI Approved :: Mozilla Public License 2.0 (MPL 2.0)
Classifier: Programming Language :: Python :: 3
Classifier: Programming Language :: Python :: 3.8
Classifier: Programming Language :: Python :: 3.9
Classifier: Programming Language :: Python :: 3.10
Classifier: Programming Language :: Python :: 3.11
Classifier: Programming Language :: Python :: 3.12
Classifier: Operating System :: OS Independent
Requires-Python: >=3.8
License-File: LICENSE
Requires-Dist: numpy
Dynamic: license-file
